cookiecutter_test_build-0.0.8.dist-info/METADATA
cookiecutter_test_build-0.0.8.dist-info/WHEEL
cookiecutter_test_build-0.0.8.dist-info/licenses/LICENSE.md
cookiecutter_test_build/__init__.py
cookiecutter_test_build/_utils.py
cookiecutter_test_build/py.typed
cookiecutter_test_build-0.0.8.dist-info/RECORD
