Metadata-Version: 2.1
Name: cookiecutter_test_build
Version: 0.0.8
Summary: Python Boilerplate contains all the boilerplate you need to create a Python package.
Author-Email: Zachary Stucke <zakstucke@gmail.com>
License: MIT
Classifier: Development Status :: 1 - Planning
Classifier: Programming Language :: Python
Classifier: Programming Language :: Python :: Implementation :: CPython
Classifier: Programming Language :: Python :: Implementation :: PyPy
Classifier: Programming Language :: Python :: 3
Classifier: Programming Language :: Python :: 3 :: Only
Classifier: Programming Language :: Python :: 3.9
Classifier: Programming Language :: Python :: 3.10
Classifier: Programming Language :: Python :: 3.11
Classifier: Programming Language :: Python :: 3.12
Classifier: License :: OSI Approved
Project-URL: Sourcecode, https://github.com/zakstucke/cookiecutter_test_build
Project-URL: Documentation, https://zakstucke.github.io/cookiecutter_test_build
Requires-Python: >=3.9
